{
  "main": {
    "id": "c6569507a57cd0e1",
    "type": "split",
    "children": [
      {
        "id": "96ba825640fdf963",
        "type": "tabs",
        "children": [
          {
            "id": "43b852ea096d19ad",
            "type": "leaf",
            "state": {
              "type": "markdown",
              "state": {
                "file": "Angular Documentation/Dependecy Injection.md",
                "mode": "source",
                "source": false
              }
            }
          },
          {
            "id": "fb312da13baf9b9c",
            "type": "leaf",
            "state": {
              "type": "markdown",
              "state": {
                "file": "Angular Documentation/Dependecy Injection.md",
                "mode": "source",
                "source": false
              }
            }
          }
        ],
        "currentTab": 1
      }
    ],
    "direction": "vertical"
  },
  "left": {
    "id": "d01734cd61272bb1",
    "type": "split",
    "children": [
      {
        "id": "d2f7f4cb8620f8ee",
        "type": "tabs",
        "children": [
          {
            "id": "a3fcc2d572ee6c92",
            "type": "leaf",
            "state": {
              "type": "file-explorer",
              "state": {
                "sortOrder": "alphabetical"
              }
            }
          },
          {
            "id": "ebb496efeaf91738",
            "type": "leaf",
            "state": {
              "type": "search",
              "state": {
                "query": "",
                "matchingCase": false,
                "explainSearch": false,
                "collapseAll": false,
                "extraContext": false,
                "sortOrder": "alphabetical"
              }
            }
          },
          {
            "id": "3aa12c19a667eac4",
            "type": "leaf",
            "state": {
              "type": "bookmarks",
              "state": {}
            }
          }
        ]
      }
    ],
    "direction": "horizontal",
    "width": 200
  },
  "right": {
    "id": "090c2c252298ab5b",
    "type": "split",
    "children": [
      {
        "id": "d69899f672662414",
        "type": "tabs",
        "children": [
          {
            "id": "0e35e33763960795",
            "type": "leaf",
            "state": {
              "type": "backlink",
              "state": {
                "file": "Angular Documentation/Dependecy Injection.md",
                "collapseAll": false,
                "extraContext": false,
                "sortOrder": "alphabetical",
                "showSearch": false,
                "searchQuery": "",
                "backlinkCollapsed": false,
                "unlinkedCollapsed": true
              }
            }
          },
          {
            "id": "ed497e26f5f4d4a4",
            "type": "leaf",
            "state": {
              "type": "outgoing-link",
              "state": {
                "file": "Angular Documentation/Dependecy Injection.md",
                "linksCollapsed": false,
                "unlinkedCollapsed": true
              }
            }
          },
          {
            "id": "4d0c73b0cde81a1d",
            "type": "leaf",
            "state": {
              "type": "tag",
              "state": {
                "sortOrder": "frequency",
                "useHierarchy": true
              }
            }
          },
          {
            "id": "8c050554241c2d19",
            "type": "leaf",
            "state": {
              "type": "outline",
              "state": {
                "file": "Angular Documentation/Dependecy Injection.md"
              }
            }
          }
        ]
      }
    ],
    "direction": "horizontal",
    "width": 300,
    "collapsed": true
  },
  "left-ribbon": {
    "hiddenItems": {
      "switcher:Open quick switcher": false,
      "graph:Open graph view": false,
      "canvas:Create new canvas": false,
      "daily-notes:Open today's daily note": false,
      "templates:Insert template": false,
      "command-palette:Open command palette": false
    }
  },
  "active": "fb312da13baf9b9c",
  "lastOpenFiles": [
    "Angular Documentation/Routing.md",
    "Angular Documentation/Dependecy Injection.md",
    "Untitled.canvas",
    "2024-09-07.md",
    "Angular Documentation/Dependency Injection/Untitled.md",
    "Angular Documentation/Dependency Injection",
    "Angular Documentation",
    "Welcome.md"
  ]
}